{"took":1,"timed_out":false,"_shards":{"total":1,"successful":1,"skipped":0,"failed":0},"posrot":{"rotx":0,"rotz":0,"roty":30,"x":-1.75,"y":0.5,"z":1.8}, "hits":{"total":1,"max_score":1.0,"hits":[{"_index":".vboard","_type":"visthreed","_id":"bubbles_Count, avg files, authors repo","_score":1.0,"_source":{"chartType":"bubbles","description":"GrimoireLab","name":"Count, avg files, authors repo","data":[{"key1":"grimoirelab/kibiter","key2":"Rashid Khan","value":33.39436210403952,"value2":3441},{"key1":"grimoirelab/GrimoireELK","key2":"Rashid Khan","value":0,"value2":0},{"key1":"grimoirelab/perceval","key2":"Rashid Khan","value":0,"value2":0},{"key1":"grimoirelab/mordred","key2":"Rashid Khan","value":0,"value2":0},{"key1":"grimoirelab/panels","key2":"Rashid Khan","value":0,"value2":0},{"key1":"grimoirelab/kibiter","key2":"Spencer Alger","value":7.793895348837209,"value2":3440},{"key1":"grimoirelab/GrimoireELK","key2":"Spencer Alger","value":0,"value2":0},{"key1":"grimoirelab/perceval","key2":"Spencer Alger","value":0,"value2":0},{"key1":"grimoirelab/mordred","key2":"Spencer Alger","value":0,"value2":0},{"key1":"grimoirelab/panels","key2":"Spencer Alger","value":0,"value2":0},{"key1":"grimoirelab/kibiter","key2":"Joe Fleming","value":1.7924845765563657,"value2":1783},{"key1":"grimoirelab/GrimoireELK","key2":"Joe Fleming","value":0,"value2":0},{"key1":"grimoirelab/perceval","key2":"Joe Fleming","value":0,"value2":0},{"key1":"grimoirelab/mordred","key2":"Joe Fleming","value":0,"value2":0},{"key1":"grimoirelab/panels","key2":"Joe Fleming","value":0,"value2":0},{"key1":"grimoirelab/kibiter","key2":"Shelby Sturgis","value":2.5743834526650757,"value2":1257},{"key1":"grimoirelab/GrimoireELK","key2":"Shelby Sturgis","value":0,"value2":0},{"key1":"grimoirelab/perceval","key2":"Shelby Sturgis","value":0,"value2":0},{"key1":"grimoirelab/mordred","key2":"Shelby Sturgis","value":0,"value2":0},{"key1":"grimoirelab/panels","key2":"Shelby Sturgis","value":0,"value2":0},{"key1":"grimoirelab/kibiter","key2":"spalger","value":9.753472222222221,"value2":1152},{"key1":"grimoirelab/GrimoireELK","key2":"spalger","value":0,"value2":0},{"key1":"grimoirelab/perceval","key2":"spalger","value":0,"value2":0},{"key1":"grimoirelab/mordred","key2":"spalger","value":0,"value2":0},{"key1":"grimoirelab/panels","key2":"spalger","value":0,"value2":0},{"key1":"grimoirelab/kibiter","key2":"Alvaro del Castillo","value":0,"value2":0},{"key1":"grimoirelab/GrimoireELK","key2":"Alvaro del Castillo","value":1.801729873586161,"value2":1503},{"key1":"grimoirelab/perceval","key2":"Alvaro del Castillo","value":2.3728813559322033,"value2":59},{"key1":"grimoirelab/mordred","key2":"Alvaro del Castillo","value":1.514344262295082,"value2":488},{"key1":"grimoirelab/panels","key2":"Alvaro del Castillo","value":1.8620689655172413,"value2":29},{"key1":"grimoirelab/kibiter","key2":"Valerio Consentino","value":0,"value2":0},{"key1":"grimoirelab/GrimoireELK","key2":"Valerio Consentino","value":1.8822314049586777,"value2":484},{"key1":"grimoirelab/perceval","key2":"Valerio Consentino","value":2.2401129943502824,"value2":354},{"key1":"grimoirelab/mordred","key2":"Valerio Consentino","value":1.572972972972973,"value2":185},{"key1":"grimoirelab/panels","key2":"Valerio Consentino","value":0.6071428571428571,"value2":28},{"key1":"grimoirelab/kibiter","key2":"Luis Cañas-Díaz","value":0,"value2":0},{"key1":"grimoirelab/GrimoireELK","key2":"Luis Cañas-Díaz","value":1.1529411764705881,"value2":85},{"key1":"grimoirelab/perceval","key2":"Luis Cañas-Díaz","value":0,"value2":0},{"key1":"grimoirelab/mordred","key2":"Luis Cañas-Díaz","value":1.2592592592592593,"value2":81},{"key1":"grimoirelab/panels","key2":"Luis Cañas-Díaz","value":0,"value2":0},{"key1":"grimoirelab/kibiter","key2":"Alberto Pérez García-Plaza","value":0,"value2":0},{"key1":"grimoirelab/GrimoireELK","key2":"Alberto Pérez García-Plaza","value":1.626865671641791,"value2":67},{"key1":"grimoirelab/perceval","key2":"Alberto Pérez García-Plaza","value":0,"value2":0},{"key1":"grimoirelab/mordred","key2":"Alberto Pérez García-Plaza","value":0,"value2":0},{"key1":"grimoirelab/panels","key2":"Alberto Pérez García-Plaza","value":2.9593220338983053,"value2":295},{"key1":"grimoirelab/kibiter","key2":"Santiago  Dueñas","value":0,"value2":0},{"key1":"grimoirelab/GrimoireELK","key2":"Santiago  Dueñas","value":0.7142857142857143,"value2":42},{"key1":"grimoirelab/perceval","key2":"Santiago  Dueñas","value":2.01625,"value2":800},{"key1":"grimoirelab/mordred","key2":"Santiago  Dueñas","value":1,"value2":37},{"key1":"grimoirelab/panels","key2":"Santiago  Dueñas","value":1.1290322580645162,"value2":31},{"key1":"grimoirelab/kibiter","key2":"Alberto Martín","value":0,"value2":0},{"key1":"grimoirelab/GrimoireELK","key2":"Alberto Martín","value":0,"value2":0},{"key1":"grimoirelab/perceval","key2":"Alberto Martín","value":1.9215686274509804,"value2":51},{"key1":"grimoirelab/mordred","key2":"Alberto Martín","value":0,"value2":0},{"key1":"grimoirelab/panels","key2":"Alberto Martín","value":0,"value2":0},{"key1":"grimoirelab/kibiter","key2":"Jesus M. Gonzalez-Barahona","value":0,"value2":0},{"key1":"grimoirelab/GrimoireELK","key2":"Jesus M. Gonzalez-Barahona","value":0,"value2":0},{"key1":"grimoirelab/perceval","key2":"Jesus M. Gonzalez-Barahona","value":4.05,"value2":20},{"key1":"grimoirelab/mordred","key2":"Jesus M. Gonzalez-Barahona","value":3.611111111111111,"value2":18},{"key1":"grimoirelab/panels","key2":"Jesus M. Gonzalez-Barahona","value":0,"value2":0},{"key1":"grimoirelab/kibiter","key2":"Daniel Izquierdo Cortazar","value":0,"value2":0},{"key1":"grimoirelab/GrimoireELK","key2":"Daniel Izquierdo Cortazar","value":0,"value2":0},{"key1":"grimoirelab/perceval","key2":"Daniel Izquierdo Cortazar","value":0,"value2":0},{"key1":"grimoirelab/mordred","key2":"Daniel Izquierdo Cortazar","value":0,"value2":0},{"key1":"grimoirelab/panels","key2":"Daniel Izquierdo Cortazar","value":1.3390410958904109,"value2":292}],"indexOfES":"git","typeOfES":"items","metricsSelected":[{"id":0,"type":"metric","aggregationType":"avg","aggregationField":"files"},{"id":1,"type":"metric","aggregationType":"count"}],"bucketsSelected":[{"id":0,"type":"bucket","aggregationType":"terms","aggregationField":"github_repo","aggregationOptions":{"size":"5"}},{"id":1,"type":"bucket","aggregationType":"terms","aggregationField":"Author_name","aggregationOptions":{"size":"5"}}]}}]}}